{
    "timestamp": "2025-03-24 22:00:29",
    "trends": {
        "IE": [
            {
                "title": "england vs latvia",
                "search_volume": "10K+\n\n1,000%",
                "started": "3 hours ago\ntrending_up\nActive",
                "related_topics": ""
            },
            {
                "title": "ryanair prime",
                "search_volume": "2K+\n\n1,000%",
                "started": "6 hours ago\ntrending_up\nActive",
                "related_topics": ""
            },
            {
                "title": "vanessa trump",
                "search_volume": "10K+\n\n1,000%",
                "started": "22 hours ago\ntrending_up\nActive",
                "related_topics": ""
            },
            {
                "title": "thunders bakery",
                "search_volume": "5K+\n\n1,000%",
                "started": "9 hours ago\ntrending_up\nActive",
                "related_topics": ""
            },
            {
                "title": "world cup qualifiers",
                "search_volume": "1K+\n\n200%",
                "started": "1 hour ago\ntrending_up\nActive",
                "related_topics": ""
            },
            {
                "title": "hamdan ballal",
                "search_volume": "500+\n\n1,000%",
                "started": "1 hour ago\ntrending_up\nActive",
                "related_topics": ""
            },
            {
                "title": "helen mcentee education",
                "search_volume": "1K+\n\n1,000%",
                "started": "1 hour ago\ntrending_up\nActive",
                "related_topics": ""
            },
            {
                "title": "poland vs malta",
                "search_volume": "500+\n\n1,000%",
                "started": "2 hours ago\ntrending_up\nActive",
                "related_topics": ""
            },
            {
                "title": "charlie bird",
                "search_volume": "200+\n\n1,000%",
                "started": "40 minutes ago\ntrending_up\nActive",
                "related_topics": ""
            },
            {
                "title": "polska \u2013 malta",
                "search_volume": "500+\n\n1,000%",
                "started": "2 hours ago\ntrending_up\nActive",
                "related_topics": ""
            },
            {
                "title": "anne enright",
                "search_volume": "200+\n\n1,000%",
                "started": "30 minutes ago\ntrending_up\nActive",
                "related_topics": ""
            },
            {
                "title": "cain velasquez",
                "search_volume": "200+\n\n1,000%",
                "started": "20 minutes ago\ntrending_up\nActive",
                "related_topics": ""
            },
            {
                "title": "is coronation street on tonight",
                "search_volume": "100+\n\n1,000%",
                "started": "30 minutes ago\ntrending_up\nActive",
                "related_topics": ""
            },
            {
                "title": "white lotus",
                "search_volume": "200+\n\n50%",
                "started": "20 minutes ago\ntrending_up\nActive",
                "related_topics": ""
            },
            {
                "title": "pete hegseth",
                "search_volume": "100+\n\n900%",
                "started": "40 minutes ago\ntrending_up\nActive",
                "related_topics": ""
            },
            {
                "title": "charlotte church",
                "search_volume": "200+\n\n1,000%",
                "started": "1 hour ago\n\nLasted 1 hr",
                "related_topics": ""
            },
            {
                "title": "ticketmaster",
                "search_volume": "2K+\n\n200%",
                "started": "5 hours ago\n\nLasted 3 hr",
                "related_topics": ""
            },
            {
                "title": "ashutosh sharma",
                "search_volume": "1K+\n\n1,000%",
                "started": "4 hours ago\n\nLasted 2 hr",
                "related_topics": ""
            },
            {
                "title": "ireland u21",
                "search_volume": "100+\n\n1,000%",
                "started": "40 minutes ago\n\nLasted 40 min",
                "related_topics": ""
            },
            {
                "title": "gaa catfish niamh farrell",
                "search_volume": "2K+\n\n1,000%",
                "started": "23 hours ago\n\nLasted 15 hr",
                "related_topics": ""
            },
            {
                "title": "penta group leo varadkar",
                "search_volume": "1K+\n\n1,000%",
                "started": "3 hours ago\n\nLasted 1 hr",
                "related_topics": ""
            },
            {
                "title": "chloe koyce",
                "search_volume": "500+\n\n200%",
                "started": "12 hours ago\n\nLasted 11 hr",
                "related_topics": ""
            },
            {
                "title": "mary berry",
                "search_volume": "200+\n\n1,000%",
                "started": "2 hours ago\n\nLasted 1 hr",
                "related_topics": ""
            },
            {
                "title": "san marino - rom\u00e2nia",
                "search_volume": "200+\n\n1,000%",
                "started": "1 hour ago\n\nLasted 1 hr",
                "related_topics": ""
            },
            {
                "title": "cameron cooper",
                "search_volume": "200+\n\n1,000%",
                "started": "3 hours ago\n\nLasted 2 hr",
                "related_topics": ""
            }
        ],
        "GB": [
            {
                "title": "cherry blossom",
                "search_volume": "1M+\n\n1,000%",
                "started": "22 hours ago\ntrending_up\nActive",
                "related_topics": ""
            },
            {
                "title": "england",
                "search_volume": "200K+\n\n1,000%",
                "started": "2 hours ago\ntrending_up\nActive",
                "related_topics": ""
            },
            {
                "title": "vanessa trump",
                "search_volume": "100K+\n\n1,000%",
                "started": "22 hours ago\ntrending_up\nActive",
                "related_topics": ""
            },
            {
                "title": "england fc",
                "search_volume": "20K+\n\n900%",
                "started": "3 hours ago\ntrending_up\nActive",
                "related_topics": ""
            },
            {
                "title": "morrisons cafe store closures",
                "search_volume": "50K+\n\n1,000%",
                "started": "3 hours ago\ntrending_up\nActive",
                "related_topics": ""
            },
            {
                "title": "morgan rogers",
                "search_volume": "10K+\n\n1,000%",
                "started": "3 hours ago\ntrending_up\nActive",
                "related_topics": ""
            },
            {
                "title": "baller league",
                "search_volume": "20K+\n\n1,000%",
                "started": "5 hours ago\ntrending_up\nActive",
                "related_topics": ""
            },
            {
                "title": "albania vs andorra",
                "search_volume": "10K+\n\n1,000%",
                "started": "3 hours ago\ntrending_up\nActive",
                "related_topics": ""
            },
            {
                "title": "hamdan ballal",
                "search_volume": "5K+\n\n1,000%",
                "started": "3 hours ago\ntrending_up\nActive",
                "related_topics": ""
            },
            {
                "title": "23andme",
                "search_volume": "10K+\n\n700%",
                "started": "14 hours ago\ntrending_up\nActive",
                "related_topics": ""
            },
            {
                "title": "ashutosh sharma",
                "search_volume": "20K+\n\n1,000%",
                "started": "5 hours ago\ntrending_up\nActive",
                "related_topics": ""
            },
            {
                "title": "mary berry",
                "search_volume": "20K+\n\n1,000%",
                "started": "15 hours ago\ntrending_up\nActive",
                "related_topics": ""
            },
            {
                "title": "poland vs malta",
                "search_volume": "5K+\n\n1,000%",
                "started": "3 hours ago\ntrending_up\nActive",
                "related_topics": ""
            },
            {
                "title": "san marino vs romania",
                "search_volume": "10K+\n\n1,000%",
                "started": "3 hours ago\ntrending_up\nActive",
                "related_topics": ""
            },
            {
                "title": "polska \u2013 malta",
                "search_volume": "5K+\n\n1,000%",
                "started": "3 hours ago\ntrending_up\nActive",
                "related_topics": ""
            },
            {
                "title": "motability cars",
                "search_volume": "10K+\n\n1,000%",
                "started": "3 hours ago\ntrending_up\nActive",
                "related_topics": ""
            },
            {
                "title": "space x",
                "search_volume": "5K+\n\n1,000%",
                "started": "1 hour ago\ntrending_up\nActive",
                "related_topics": ""
            },
            {
                "title": "chris stark",
                "search_volume": "5K+\n\n1,000%",
                "started": "4 hours ago\ntrending_up\nActive",
                "related_topics": ""
            },
            {
                "title": "england u-21 vs portugal u-21",
                "search_volume": "5K+\n\n1,000%",
                "started": "3 hours ago\ntrending_up\nActive",
                "related_topics": ""
            },
            {
                "title": "england u21",
                "search_volume": "5K+\n\n1,000%",
                "started": "2 hours ago\ntrending_up\nActive",
                "related_topics": ""
            },
            {
                "title": "harry kane",
                "search_volume": "5K+\n\n700%",
                "started": "1 hour ago\ntrending_up\nActive",
                "related_topics": ""
            },
            {
                "title": "emma raducanu",
                "search_volume": "20K+\n\n600%",
                "started": "23 hours ago\ntrending_up\nActive",
                "related_topics": ""
            },
            {
                "title": "usha vance",
                "search_volume": "5K+\n\n700%",
                "started": "15 hours ago\ntrending_up\nActive",
                "related_topics": ""
            },
            {
                "title": "wwe raw",
                "search_volume": "2K+\n\n900%",
                "started": "4 hours ago\ntrending_up\nActive",
                "related_topics": ""
            },
            {
                "title": "rogers england",
                "search_volume": "2K+\n\n800%",
                "started": "2 hours ago\ntrending_up\nActive",
                "related_topics": ""
            }
        ],
        "US": [
            {
                "title": "pete hegseth",
                "search_volume": "100K+\n\n1,000%",
                "started": "4 hours ago\ntrending_up\nActive",
                "related_topics": ""
            },
            {
                "title": "tiger woods girlfriend",
                "search_volume": "1M+\n\n1,000%",
                "started": "23 hours ago\ntrending_up\nActive",
                "related_topics": ""
            },
            {
                "title": "mia love",
                "search_volume": "100K+\n\n1,000%",
                "started": "19 hours ago\ntrending_up\nActive",
                "related_topics": ""
            },
            {
                "title": "hamdan ballal",
                "search_volume": "20K+\n\n1,000%",
                "started": "3 hours ago\ntrending_up\nActive",
                "related_topics": ""
            },
            {
                "title": "england vs latvia",
                "search_volume": "50K+\n\n1,000%",
                "started": "3 hours ago\ntrending_up\nActive",
                "related_topics": ""
            },
            {
                "title": "davis mcclendon",
                "search_volume": "100K+\n\n1,000%",
                "started": "20 hours ago\ntrending_up\nActive",
                "related_topics": ""
            },
            {
                "title": "cain velasquez",
                "search_volume": "10K+\n\n400%",
                "started": "7 hours ago\ntrending_up\nActive",
                "related_topics": ""
            },
            {
                "title": "23andme delete data",
                "search_volume": "50K+\n\n100%",
                "started": "9 hours ago\ntrending_up\nActive",
                "related_topics": ""
            },
            {
                "title": "ford f 150 investigation",
                "search_volume": "10K+\n\n800%",
                "started": "2 hours ago\ntrending_up\nActive",
                "related_topics": ""
            },
            {
                "title": "destined rivals",
                "search_volume": "20K+\n\n200%",
                "started": "8 hours ago\ntrending_up\nActive",
                "related_topics": ""
            },
            {
                "title": "iowa women's basketball",
                "search_volume": "20K+\n\n400%",
                "started": "2 hours ago\ntrending_up\nActive",
                "related_topics": ""
            },
            {
                "title": "ashutosh sharma",
                "search_volume": "20K+\n\n900%",
                "started": "5 hours ago\ntrending_up\nActive",
                "related_topics": ""
            },
            {
                "title": "alina habba",
                "search_volume": "20K+\n\n700%",
                "started": "6 hours ago\ntrending_up\nActive",
                "related_topics": ""
            },
            {
                "title": "brazil vs argentina",
                "search_volume": "20K+\n\n100%",
                "started": "23 hours ago\ntrending_up\nActive",
                "related_topics": ""
            },
            {
                "title": "spooky story nyt",
                "search_volume": "50K+\n\n300%",
                "started": "23 hours ago\ntrending_up\nActive",
                "related_topics": ""
            },
            {
                "title": "kat abughazaleh",
                "search_volume": "10K+\n\n200%",
                "started": "8 hours ago\ntrending_up\nActive",
                "related_topics": ""
            },
            {
                "title": "niko medved",
                "search_volume": "100K+\n\n300%",
                "started": "22 hours ago\ntrending_up\nActive",
                "related_topics": ""
            },
            {
                "title": "coco gauff",
                "search_volume": "10K+\n\n1,000%",
                "started": "2 hours ago\ntrending_up\nActive",
                "related_topics": ""
            },
            {
                "title": "inglaterra - letonia",
                "search_volume": "5K+\n\n400%",
                "started": "3 hours ago\ntrending_up\nActive",
                "related_topics": ""
            },
            {
                "title": "magda linette",
                "search_volume": "5K+\n\n300%",
                "started": "2 hours ago\ntrending_up\nActive",
                "related_topics": ""
            },
            {
                "title": "e zpass toll scam",
                "search_volume": "20K+\n\n100%",
                "started": "7 hours ago\ntrending_up\nActive",
                "related_topics": ""
            },
            {
                "title": "poland vs malta",
                "search_volume": "5K+\n\n300%",
                "started": "2 hours ago\ntrending_up\nActive",
                "related_topics": ""
            },
            {
                "title": "tony todd",
                "search_volume": "5K+\n\n200%",
                "started": "4 hours ago\ntrending_up\nActive",
                "related_topics": ""
            },
            {
                "title": "drake bell",
                "search_volume": "5K+\n\n75%",
                "started": "7 hours ago\ntrending_up\nActive",
                "related_topics": ""
            },
            {
                "title": "trump portrait colorado",
                "search_volume": "20K+\n\n100%",
                "started": "18 hours ago\ntrending_up\nActive",
                "related_topics": ""
            }
        ]
    }
}