{
    "timestamp": "2025-06-01 00:00:28",
    "trends": {
        "IE": [
            {
                "title": "psg vs inter",
                "search_volume": "20K+\n\n1,000%",
                "started": "5 hours ago\ntrending_up\nActive",
                "related_topics": ""
            },
            {
                "title": "psg",
                "search_volume": "10K+\n\n1,000%",
                "started": "7 hours ago\ntrending_up\nActive",
                "related_topics": ""
            },
            {
                "title": "munster v sharks",
                "search_volume": "20K+\n\n1,000%",
                "started": "12 hours ago\ntrending_up\nActive",
                "related_topics": ""
            },
            {
                "title": "luis enrique",
                "search_volume": "5K+\n\n1,000%",
                "started": "4 hours ago\ntrending_up\nActive",
                "related_topics": ""
            },
            {
                "title": "greg monks missing",
                "search_volume": "5K+\n\n1,000%",
                "started": "16 hours ago\ntrending_up\nActive",
                "related_topics": ""
            },
            {
                "title": "dunnes stores ysl shoe dupes",
                "search_volume": "2K+\n\n1,000%",
                "started": "8 hours ago\ntrending_up\nActive",
                "related_topics": ""
            },
            {
                "title": "luis enrique daughter",
                "search_volume": "5K+\n\n1,000%",
                "started": "4 hours ago\ntrending_up\nActive",
                "related_topics": ""
            },
            {
                "title": "mayo v tyrone",
                "search_volume": "5K+\n\n1,000%",
                "started": "7 hours ago\ntrending_up\nActive",
                "related_topics": ""
            },
            {
                "title": "cork v kerry",
                "search_volume": "10K+\n\n1,000%",
                "started": "11 hours ago\ntrending_up\nActive",
                "related_topics": ""
            },
            {
                "title": "euromillions ireland",
                "search_volume": "2K+\n\n1,000%",
                "started": "11 hours ago\ntrending_up\nActive",
                "related_topics": ""
            },
            {
                "title": "billie piper",
                "search_volume": "1K+\n\n1,000%",
                "started": "3 hours ago\ntrending_up\nActive",
                "related_topics": ""
            },
            {
                "title": "new covid variant ireland symptoms",
                "search_volume": "500+\n\n1,000%",
                "started": "3 hours ago\ntrending_up\nActive",
                "related_topics": ""
            },
            {
                "title": "valerie mahaffey",
                "search_volume": "1K+\n\n1,000%",
                "started": "10 hours ago\ntrending_up\nActive",
                "related_topics": ""
            },
            {
                "title": "dept q",
                "search_volume": "1K+\n\n600%",
                "started": "2 hours ago\ntrending_up\nActive",
                "related_topics": ""
            },
            {
                "title": "cork city marathon 2025",
                "search_volume": "1K+\n\n300%",
                "started": "5 hours ago\ntrending_up\nActive",
                "related_topics": ""
            },
            {
                "title": "leinster v scarlets",
                "search_volume": "10K+\n\n1,000%",
                "started": "14 hours ago\n\nLasted 12 hr",
                "related_topics": ""
            },
            {
                "title": "who won britain's got talent 2025",
                "search_volume": "1K+\n\n1,000%",
                "started": "1 hour ago\ntrending_up\nActive",
                "related_topics": ""
            },
            {
                "title": "hakimi",
                "search_volume": "2K+\n\n1,000%",
                "started": "3 hours ago\n\nLasted 3 hr",
                "related_topics": ""
            },
            {
                "title": "vitinha",
                "search_volume": "1K+\n\n1,000%",
                "started": "3 hours ago\n\nLasted 3 hr",
                "related_topics": ""
            },
            {
                "title": "roscommon v meath",
                "search_volume": "2K+\n\n1,000%",
                "started": "7 hours ago\n\nLasted 6 hr",
                "related_topics": ""
            },
            {
                "title": "shane lowry",
                "search_volume": "500+\n\n100%",
                "started": "1 hour ago\ntrending_up\nActive",
                "related_topics": ""
            },
            {
                "title": "tyrone v mayo",
                "search_volume": "2K+\n\n1,000%",
                "started": "5 hours ago\n\nLasted 5 hr",
                "related_topics": ""
            },
            {
                "title": "bruce springsteen",
                "search_volume": "500+\n\n1,000%",
                "started": "2 hours ago\n\nLasted 2 hr",
                "related_topics": ""
            },
            {
                "title": "timothee chalamet",
                "search_volume": "100+\n\n800%",
                "started": "1 hour ago\ntrending_up\nActive",
                "related_topics": ""
            },
            {
                "title": "kvaratskhelia",
                "search_volume": "1K+\n\n1,000%",
                "started": "3 hours ago\n\nLasted 3 hr",
                "related_topics": ""
            }
        ],
        "GB": [
            {
                "title": "champions league final",
                "search_volume": "500K+\n\n500%",
                "started": "15 hours ago\ntrending_up\nActive",
                "related_topics": ""
            },
            {
                "title": "billie piper",
                "search_volume": "100K+\n\n1,000%",
                "started": "4 hours ago\ntrending_up\nActive",
                "related_topics": ""
            },
            {
                "title": "psg",
                "search_volume": "200K+\n\n1,000%",
                "started": "23 hours ago\ntrending_up\nActive",
                "related_topics": ""
            },
            {
                "title": "luis enrique",
                "search_volume": "50K+\n\n1,000%",
                "started": "17 hours ago\ntrending_up\nActive",
                "related_topics": ""
            },
            {
                "title": "who won bgt 2025",
                "search_volume": "200K+\n\n1,000%",
                "started": "3 hours ago\ntrending_up\nActive",
                "related_topics": ""
            },
            {
                "title": "luis enrique daughter",
                "search_volume": "50K+\n\n1,000%",
                "started": "5 hours ago\ntrending_up\nActive",
                "related_topics": ""
            },
            {
                "title": "valerie mahaffey",
                "search_volume": "20K+\n\n1,000%",
                "started": "12 hours ago\ntrending_up\nActive",
                "related_topics": ""
            },
            {
                "title": "bruce springsteen",
                "search_volume": "20K+\n\n1,000%",
                "started": "3 hours ago\ntrending_up\nActive",
                "related_topics": ""
            },
            {
                "title": "hakimi",
                "search_volume": "20K+\n\n1,000%",
                "started": "4 hours ago\ntrending_up\nActive",
                "related_topics": ""
            },
            {
                "title": "mayulu",
                "search_volume": "20K+\n\n1,000%",
                "started": "2 hours ago\ntrending_up\nActive",
                "related_topics": ""
            },
            {
                "title": "nigeria vs jamaica",
                "search_volume": "50K+\n\n1,000%",
                "started": "14 hours ago\ntrending_up\nActive",
                "related_topics": ""
            },
            {
                "title": "sky q free gift",
                "search_volume": "10K+\n\n1,000%",
                "started": "9 hours ago\ntrending_up\nActive",
                "related_topics": ""
            },
            {
                "title": "british airways cabin crew",
                "search_volume": "10K+\n\n1,000%",
                "started": "2 hours ago\ntrending_up\nActive",
                "related_topics": ""
            },
            {
                "title": "kvaratskhelia",
                "search_volume": "10K+\n\n1,000%",
                "started": "4 hours ago\ntrending_up\nActive",
                "related_topics": ""
            },
            {
                "title": "miss world 2025 contestants",
                "search_volume": "10K+\n\n1,000%",
                "started": "4 hours ago\ntrending_up\nActive",
                "related_topics": ""
            },
            {
                "title": "dembele",
                "search_volume": "10K+\n\n1,000%",
                "started": "5 hours ago\ntrending_up\nActive",
                "related_topics": ""
            },
            {
                "title": "simon yates",
                "search_volume": "20K+\n\n1,000%",
                "started": "9 hours ago\ntrending_up\nActive",
                "related_topics": ""
            },
            {
                "title": "british soap awards 2025",
                "search_volume": "5K+\n\n700%",
                "started": "7 hours ago\ntrending_up\nActive",
                "related_topics": ""
            },
            {
                "title": "see how they run",
                "search_volume": "5K+\n\n1,000%",
                "started": "7 hours ago\ntrending_up\nActive",
                "related_topics": ""
            },
            {
                "title": "stranger things season 5 trailer",
                "search_volume": "20K+\n\n300%",
                "started": "22 hours ago\ntrending_up\nActive",
                "related_topics": ""
            },
            {
                "title": "simone inzaghi",
                "search_volume": "10K+\n\n1,000%",
                "started": "5 hours ago\ntrending_up\nActive",
                "related_topics": ""
            },
            {
                "title": "dani dyer",
                "search_volume": "10K+\n\n1,000%",
                "started": "6 hours ago\ntrending_up\nActive",
                "related_topics": ""
            },
            {
                "title": "linkin park",
                "search_volume": "10K+\n\n1,000%",
                "started": "4 hours ago\ntrending_up\nActive",
                "related_topics": ""
            },
            {
                "title": "pag",
                "search_volume": "5K+\n\n1,000%",
                "started": "5 hours ago\ntrending_up\nActive",
                "related_topics": ""
            },
            {
                "title": "d\u00e9sir\u00e9 dou\u00e9",
                "search_volume": "5K+\n\n1,000%",
                "started": "4 hours ago\ntrending_up\nActive",
                "related_topics": ""
            }
        ],
        "US": [
            {
                "title": "valerie mahaffey",
                "search_volume": "200K+\n\n1,000%",
                "started": "16 hours ago\ntrending_up\nActive",
                "related_topics": ""
            },
            {
                "title": "psg - inter",
                "search_volume": "500K+\n\n1,000%",
                "started": "4 hours ago\ntrending_up\nActive",
                "related_topics": ""
            },
            {
                "title": "psg",
                "search_volume": "200K+\n\n1,000%",
                "started": "11 hours ago\ntrending_up\nActive",
                "related_topics": ""
            },
            {
                "title": "stranger things season 5 release date",
                "search_volume": "100K+\n\n200%",
                "started": "22 hours ago\ntrending_up\nActive",
                "related_topics": ""
            },
            {
                "title": "tigers vs royals",
                "search_volume": "50K+\n\n1,000%",
                "started": "23 hours ago\ntrending_up\nActive",
                "related_topics": ""
            },
            {
                "title": "luis enrique",
                "search_volume": "50K+\n\n1,000%",
                "started": "5 hours ago\ntrending_up\nActive",
                "related_topics": ""
            },
            {
                "title": "cardinals vs rangers",
                "search_volume": "20K+\n\n700%",
                "started": "23 hours ago\ntrending_up\nActive",
                "related_topics": ""
            },
            {
                "title": "british airways flight attendant",
                "search_volume": "20K+\n\n1,000%",
                "started": "5 hours ago\ntrending_up\nActive",
                "related_topics": ""
            },
            {
                "title": "$3000 irs tax refund schedule 2025",
                "search_volume": "50K+\n\n1,000%",
                "started": "9 hours ago\ntrending_up\nActive",
                "related_topics": ""
            },
            {
                "title": "lafc vs america",
                "search_volume": "50K+\n\n200%",
                "started": "23 hours ago\ntrending_up\nActive",
                "related_topics": ""
            },
            {
                "title": "usa vs china",
                "search_volume": "20K+\n\n1,000%",
                "started": "2 hours ago\ntrending_up\nActive",
                "related_topics": ""
            },
            {
                "title": "billie piper",
                "search_volume": "20K+\n\n800%",
                "started": "4 hours ago\ntrending_up\nActive",
                "related_topics": ""
            },
            {
                "title": "rihanna",
                "search_volume": "20K+\n\n600%",
                "started": "6 hours ago\ntrending_up\nActive",
                "related_topics": ""
            },
            {
                "title": "mykale baker burger king",
                "search_volume": "20K+\n\n500%",
                "started": "23 hours ago\ntrending_up\nActive",
                "related_topics": ""
            },
            {
                "title": "oklahoma softball",
                "search_volume": "20K+\n\n100%",
                "started": "3 hours ago\ntrending_up\nActive",
                "related_topics": ""
            },
            {
                "title": "luis enrique daughter",
                "search_volume": "20K+\n\n1,000%",
                "started": "4 hours ago\ntrending_up\nActive",
                "related_topics": ""
            },
            {
                "title": "hakimi",
                "search_volume": "20K+\n\n1,000%",
                "started": "4 hours ago\ntrending_up\nActive",
                "related_topics": ""
            },
            {
                "title": "twins vs mariners",
                "search_volume": "20K+\n\n700%",
                "started": "21 hours ago\ntrending_up\nActive",
                "related_topics": ""
            },
            {
                "title": "d\u00e9sir\u00e9 dou\u00e9",
                "search_volume": "10K+\n\n1,000%",
                "started": "4 hours ago\ntrending_up\nActive",
                "related_topics": ""
            },
            {
                "title": "oregon baseball",
                "search_volume": "20K+\n\n200%",
                "started": "21 hours ago\ntrending_up\nActive",
                "related_topics": ""
            },
            {
                "title": "jamaica vs nigeria",
                "search_volume": "20K+\n\n800%",
                "started": "8 hours ago\ntrending_up\nActive",
                "related_topics": ""
            },
            {
                "title": "jack nicklaus",
                "search_volume": "5K+\n\n1,000%",
                "started": "1 hour ago\ntrending_up\nActive",
                "related_topics": ""
            },
            {
                "title": "belmont stakes 2025",
                "search_volume": "20K+\n\n100%",
                "started": "11 hours ago\ntrending_up\nActive",
                "related_topics": ""
            },
            {
                "title": "khvicha kvaratskhelia",
                "search_volume": "10K+\n\n500%",
                "started": "4 hours ago\ntrending_up\nActive",
                "related_topics": ""
            },
            {
                "title": "opal suchata chuangsri miss world",
                "search_volume": "10K+\n\n500%",
                "started": "1 hour ago\ntrending_up\nActive",
                "related_topics": ""
            }
        ]
    }
}