{
    "timestamp": "2025-06-06 13:30:27",
    "trends": {
        "IE": [
            {
                "title": "elon musk",
                "search_volume": "20K+\n\n1,000%",
                "started": "17 hours ago\ntrending_up\nActive",
                "related_topics": ""
            },
            {
                "title": "ryanair flight emergency landing",
                "search_volume": "2K+\n\n1,000%",
                "started": "16 hours ago\ntrending_up\nActive",
                "related_topics": ""
            },
            {
                "title": "eid mubarak",
                "search_volume": "2K+\n\n400%",
                "started": "6 hours ago\ntrending_up\nActive",
                "related_topics": ""
            },
            {
                "title": "ireland heatwave june forecast",
                "search_volume": "2K+\n\n1,000%",
                "started": "17 hours ago\ntrending_up\nActive",
                "related_topics": ""
            },
            {
                "title": "diane moloney listowel spain",
                "search_volume": "500+\n\n1,000%",
                "started": "5 hours ago\ntrending_up\nActive",
                "related_topics": ""
            },
            {
                "title": "france vs spain",
                "search_volume": "10K+\n\n1,000%",
                "started": "19 hours ago\n\nLasted 15 hr",
                "related_topics": ""
            },
            {
                "title": "robert pether iraq",
                "search_volume": "200+\n\n1,000%",
                "started": "50 minutes ago\ntrending_up\nActive",
                "related_topics": ""
            },
            {
                "title": "ecuador vs brazil",
                "search_volume": "2K+\n\n900%",
                "started": "14 hours ago\n\nLasted 10 hr",
                "related_topics": ""
            },
            {
                "title": "sharlene mawdsley father",
                "search_volume": "5K+\n\n1,000%",
                "started": "19 hours ago\n\nLasted 15 hr",
                "related_topics": ""
            },
            {
                "title": "chile vs argentina",
                "search_volume": "500+\n\n800%",
                "started": "10 hours ago\n\nLasted 7 hr",
                "related_topics": ""
            },
            {
                "title": "amanda brunker",
                "search_volume": "1K+\n\n1,000%",
                "started": "19 hours ago\n\nLasted 15 hr",
                "related_topics": ""
            },
            {
                "title": "thunder vs pacers",
                "search_volume": "1K+\n\n900%",
                "started": "9 hours ago\n\nLasted 5 hr",
                "related_topics": ""
            },
            {
                "title": "leaving certificate",
                "search_volume": "1K+\n\n900%",
                "started": "23 hours ago\n\nLasted 18 hr",
                "related_topics": ""
            },
            {
                "title": "ginny and georgia",
                "search_volume": "2K+\n\n300%",
                "started": "19 hours ago\n\nLasted 10 hr",
                "related_topics": ""
            },
            {
                "title": "sam thompson",
                "search_volume": "100+\n\n900%",
                "started": "2 hours ago\n\nLasted 1 hr",
                "related_topics": ""
            },
            {
                "title": "canadian open",
                "search_volume": "500+\n\n700%",
                "started": "18 hours ago\n\nLasted 12 hr",
                "related_topics": ""
            },
            {
                "title": "cherki",
                "search_volume": "1K+\n\n1,000%",
                "started": "15 hours ago\n\nLasted 9 hr",
                "related_topics": ""
            },
            {
                "title": "world cup qualifiers",
                "search_volume": "200+\n\n300%",
                "started": "12 hours ago\n\nLasted 8 hr",
                "related_topics": ""
            },
            {
                "title": "sabalenka",
                "search_volume": "1K+\n\n1,000%",
                "started": "23 hours ago\n\nLasted 5 hr",
                "related_topics": ""
            },
            {
                "title": "ecb cuts interest rates",
                "search_volume": "500+\n\n600%",
                "started": "15 hours ago\n\nLasted 10 hr",
                "related_topics": ""
            },
            {
                "title": "dragon spacecraft",
                "search_volume": "500+\n\n900%",
                "started": "16 hours ago\n\nLasted 8 hr",
                "related_topics": ""
            },
            {
                "title": "tsla",
                "search_volume": "200+\n\n500%",
                "started": "15 hours ago\n\nLasted 11 hr",
                "related_topics": ""
            },
            {
                "title": "david jason",
                "search_volume": "500+\n\n1,000%",
                "started": "15 hours ago\n\nLasted 8 hr",
                "related_topics": ""
            },
            {
                "title": "macklemore cork",
                "search_volume": "500+\n\n200%",
                "started": "22 hours ago\n\nLasted 7 hr",
                "related_topics": ""
            },
            {
                "title": "coco gauff",
                "search_volume": "500+\n\n1,000%",
                "started": "20 hours ago\n\nLasted 3 hr",
                "related_topics": ""
            }
        ],
        "GB": [
            {
                "title": "elon musk",
                "search_volume": "200K+\n\n1,000%",
                "started": "17 hours ago\ntrending_up\nActive",
                "related_topics": ""
            },
            {
                "title": "natwest online banking",
                "search_volume": "50K+\n\n800%",
                "started": "4 hours ago\ntrending_up\nActive",
                "related_topics": ""
            },
            {
                "title": "eid mubarak 2025",
                "search_volume": "100K+\n\n1,000%",
                "started": "20 hours ago\ntrending_up\nActive",
                "related_topics": ""
            },
            {
                "title": "zia yusuf",
                "search_volume": "50K+\n\n1,000%",
                "started": "24 hours ago\ntrending_up\nActive",
                "related_topics": ""
            },
            {
                "title": "david beckham",
                "search_volume": "20K+\n\n1,000%",
                "started": "15 hours ago\ntrending_up\nActive",
                "related_topics": ""
            },
            {
                "title": "hamilton by election results",
                "search_volume": "20K+\n\n1,000%",
                "started": "13 hours ago\ntrending_up\nActive",
                "related_topics": ""
            },
            {
                "title": "spain v france",
                "search_volume": "100K+\n\n1,000%",
                "started": "20 hours ago\ntrending_up\nActive",
                "related_topics": ""
            },
            {
                "title": "brazil fc",
                "search_volume": "20K+\n\n1,000%",
                "started": "16 hours ago\ntrending_up\nActive",
                "related_topics": ""
            },
            {
                "title": "is it eid today",
                "search_volume": "20K+\n\n1,000%",
                "started": "12 hours ago\ntrending_up\nActive",
                "related_topics": ""
            },
            {
                "title": "tom felton",
                "search_volume": "20K+\n\n900%",
                "started": "23 hours ago\ntrending_up\nActive",
                "related_topics": ""
            },
            {
                "title": "cherki",
                "search_volume": "10K+\n\n600%",
                "started": "16 hours ago\ntrending_up\nActive",
                "related_topics": ""
            },
            {
                "title": "chile vs argentina",
                "search_volume": "10K+\n\n1,000%",
                "started": "12 hours ago\ntrending_up\nActive",
                "related_topics": ""
            },
            {
                "title": "manchild lyrics",
                "search_volume": "10K+\n\n600%",
                "started": "12 hours ago\ntrending_up\nActive",
                "related_topics": ""
            },
            {
                "title": "amelia flanagan",
                "search_volume": "5K+\n\n800%",
                "started": "17 hours ago\ntrending_up\nActive",
                "related_topics": ""
            },
            {
                "title": "predator killer of killers",
                "search_volume": "2K+\n\n300%",
                "started": "6 hours ago\ntrending_up\nActive",
                "related_topics": ""
            },
            {
                "title": "itv british soap awards",
                "search_volume": "20K+\n\n900%",
                "started": "14 hours ago\ntrending_up\nActive",
                "related_topics": ""
            },
            {
                "title": "dragon spacecraft",
                "search_volume": "10K+\n\n900%",
                "started": "16 hours ago\ntrending_up\nActive",
                "related_topics": ""
            },
            {
                "title": "emmanuel gyamfi",
                "search_volume": "1K+\n\n1,000%",
                "started": "1 hour ago\ntrending_up\nActive",
                "related_topics": ""
            },
            {
                "title": "armin pecsi",
                "search_volume": "1K+\n\n1,000%",
                "started": "1 hour ago\ntrending_up\nActive",
                "related_topics": ""
            },
            {
                "title": "alien earth",
                "search_volume": "2K+\n\n300%",
                "started": "22 hours ago\ntrending_up\nActive",
                "related_topics": ""
            },
            {
                "title": "cmat",
                "search_volume": "2K+\n\n200%",
                "started": "7 hours ago\ntrending_up\nActive",
                "related_topics": ""
            },
            {
                "title": "argentina fc",
                "search_volume": "2K+\n\n300%",
                "started": "15 hours ago\ntrending_up\nActive",
                "related_topics": ""
            },
            {
                "title": "london stadium",
                "search_volume": "2K+\n\n100%",
                "started": "4 hours ago\ntrending_up\nActive",
                "related_topics": ""
            },
            {
                "title": "argentina national football team",
                "search_volume": "2K+\n\n300%",
                "started": "15 hours ago\ntrending_up\nActive",
                "related_topics": ""
            },
            {
                "title": "danny cadamarteri",
                "search_volume": "2K+\n\n200%",
                "started": "14 hours ago\ntrending_up\nActive",
                "related_topics": ""
            }
        ],
        "US": [
            {
                "title": "tesla stock",
                "search_volume": "2M+\n\n1,000%",
                "started": "19 hours ago\ntrending_up\nActive",
                "related_topics": ""
            },
            {
                "title": "aaron rodgers",
                "search_volume": "500K+\n\n1,000%",
                "started": "17 hours ago\ntrending_up\nActive",
                "related_topics": ""
            },
            {
                "title": "nba finals score",
                "search_volume": "1M+\n\n1,000%",
                "started": "12 hours ago\ntrending_up\nActive",
                "related_topics": ""
            },
            {
                "title": "chile vs argentina",
                "search_volume": "100K+\n\n1,000%",
                "started": "15 hours ago\ntrending_up\nActive",
                "related_topics": ""
            },
            {
                "title": "dragon spacecraft",
                "search_volume": "100K+\n\n1,000%",
                "started": "16 hours ago\ntrending_up\nActive",
                "related_topics": ""
            },
            {
                "title": "tom felton",
                "search_volume": "50K+\n\n600%",
                "started": "24 hours ago\ntrending_up\nActive",
                "related_topics": ""
            },
            {
                "title": "manchild sabrina carpenter lyrics",
                "search_volume": "50K+\n\n1,000%",
                "started": "12 hours ago\ntrending_up\nActive",
                "related_topics": ""
            },
            {
                "title": "eid mubarak",
                "search_volume": "20K+\n\n400%",
                "started": "17 hours ago\ntrending_up\nActive",
                "related_topics": ""
            },
            {
                "title": "chile - argentina",
                "search_volume": "100K+\n\n1,000%",
                "started": "12 hours ago\ntrending_up\nActive",
                "related_topics": ""
            },
            {
                "title": "spain vs portugal",
                "search_volume": "20K+\n\n500%",
                "started": "15 hours ago\ntrending_up\nActive",
                "related_topics": ""
            },
            {
                "title": "ecuador - brasil",
                "search_volume": "50K+\n\n1,000%",
                "started": "14 hours ago\ntrending_up\nActive",
                "related_topics": ""
            },
            {
                "title": "ryan gosling black panther",
                "search_volume": "20K+\n\n400%",
                "started": "14 hours ago\ntrending_up\nActive",
                "related_topics": ""
            },
            {
                "title": "dunkin donuts national doughnut day",
                "search_volume": "20K+\n\n900%",
                "started": "7 hours ago\ntrending_up\nActive",
                "related_topics": ""
            },
            {
                "title": "daphne joy",
                "search_volume": "20K+\n\n400%",
                "started": "17 hours ago\ntrending_up\nActive",
                "related_topics": ""
            },
            {
                "title": "brasil vs",
                "search_volume": "100K+\n\n500%",
                "started": "15 hours ago\ntrending_up\nActive",
                "related_topics": ""
            },
            {
                "title": "russell wilson",
                "search_volume": "20K+\n\n700%",
                "started": "17 hours ago\ntrending_up\nActive",
                "related_topics": ""
            },
            {
                "title": "dday",
                "search_volume": "10K+\n\n200%",
                "started": "11 hours ago\ntrending_up\nActive",
                "related_topics": ""
            },
            {
                "title": "justin ishbia",
                "search_volume": "20K+\n\n600%",
                "started": "19 hours ago\ntrending_up\nActive",
                "related_topics": ""
            },
            {
                "title": "lubbock tornado",
                "search_volume": "50K+\n\n700%",
                "started": "12 hours ago\ntrending_up\nActive",
                "related_topics": ""
            },
            {
                "title": "circle stock",
                "search_volume": "50K+\n\n300%",
                "started": "23 hours ago\ntrending_up\nActive",
                "related_topics": ""
            },
            {
                "title": "predator killer of killers",
                "search_volume": "10K+\n\n300%",
                "started": "14 hours ago\ntrending_up\nActive",
                "related_topics": ""
            },
            {
                "title": "steve bannon",
                "search_volume": "20K+\n\n500%",
                "started": "15 hours ago\ntrending_up\nActive",
                "related_topics": ""
            },
            {
                "title": "norman hutchins",
                "search_volume": "10K+\n\n400%",
                "started": "15 hours ago\ntrending_up\nActive",
                "related_topics": ""
            },
            {
                "title": "oliver anthony",
                "search_volume": "10K+\n\n200%",
                "started": "19 hours ago\ntrending_up\nActive",
                "related_topics": ""
            },
            {
                "title": "alien earth",
                "search_volume": "20K+\n\n300%",
                "started": "23 hours ago\ntrending_up\nActive",
                "related_topics": ""
            }
        ]
    }
}