{
    "timestamp": "2025-04-23 12:30:28",
    "trends": {
        "IE": [
            {
                "title": "intel layoffs",
                "search_volume": "2K+\n\n1,000%",
                "started": "2 hours ago\ntrending_up\nActive",
                "related_topics": ""
            },
            {
                "title": "istanbul",
                "search_volume": "500+\n\n1,000%",
                "started": "50 minutes ago\ntrending_up\nActive",
                "related_topics": ""
            },
            {
                "title": "man city vs aston villa",
                "search_volume": "20K+\n\n1,000%",
                "started": "17 hours ago\n\nLasted 16 hr",
                "related_topics": ""
            },
            {
                "title": "istanbul earthquake",
                "search_volume": "200+\n\n1,000%",
                "started": "40 minutes ago\ntrending_up\nActive",
                "related_topics": ""
            },
            {
                "title": "barcelona vs mallorca",
                "search_volume": "2K+\n\n1,000%",
                "started": "16 hours ago\n\nLasted 14 hr",
                "related_topics": ""
            },
            {
                "title": "pahalgam",
                "search_volume": "2K+\n\n700%",
                "started": "18 hours ago\n\nLasted 17 hr",
                "related_topics": ""
            },
            {
                "title": "today fm top 500 songs",
                "search_volume": "1K+\n\n1,000%",
                "started": "17 hours ago\n\nLasted 14 hr",
                "related_topics": ""
            },
            {
                "title": "tesla share price",
                "search_volume": "2K+\n\n200%",
                "started": "14 hours ago\n\nLasted 10 hr",
                "related_topics": ""
            },
            {
                "title": "nantes vs psg",
                "search_volume": "2K+\n\n1,000%",
                "started": "17 hours ago\n\nLasted 13 hr",
                "related_topics": ""
            },
            {
                "title": "lakers vs timberwolves",
                "search_volume": "1K+\n\n700%",
                "started": "8 hours ago\n\nLasted 5 hr",
                "related_topics": ""
            },
            {
                "title": "heatwave ireland",
                "search_volume": "2K+\n\n1,000%",
                "started": "23 hours ago\n\nLasted 10 hr",
                "related_topics": ""
            },
            {
                "title": "sophie nyweide",
                "search_volume": "500+\n\n700%",
                "started": "15 hours ago\n\nLasted 14 hr",
                "related_topics": ""
            },
            {
                "title": "crash m9 carlow",
                "search_volume": "1K+\n\n800%",
                "started": "14 hours ago\n\nLasted 13 hr",
                "related_topics": ""
            },
            {
                "title": "st georges day",
                "search_volume": "200+\n\n1,000%",
                "started": "3 hours ago\n\nLasted 2 hr",
                "related_topics": ""
            },
            {
                "title": "m&s cyber incident",
                "search_volume": "2K+\n\n1,000%",
                "started": "16 hours ago\n\nLasted 5 hr",
                "related_topics": ""
            },
            {
                "title": "kneecap",
                "search_volume": "1K+\n\n200%",
                "started": "17 hours ago\n\nLasted 15 hr",
                "related_topics": ""
            },
            {
                "title": "ticketmaster",
                "search_volume": "200+\n\n100%",
                "started": "2 hours ago\n\nLasted 1 hr",
                "related_topics": ""
            },
            {
                "title": "oblivion",
                "search_volume": "2K+\n\n400%",
                "started": "20 hours ago\n\nLasted 5 hr",
                "related_topics": ""
            },
            {
                "title": "thunderbolts",
                "search_volume": "200+\n\n400%",
                "started": "11 hours ago\n\nLasted 10 hr",
                "related_topics": ""
            },
            {
                "title": "ronnie o'sullivan",
                "search_volume": "1K+\n\n300%",
                "started": "21 hours ago\n\nLasted 16 hr",
                "related_topics": ""
            },
            {
                "title": "angelica big brother",
                "search_volume": "1K+\n\n1,000%",
                "started": "15 hours ago\n\nLasted 7 hr",
                "related_topics": ""
            },
            {
                "title": "lsg vs dc",
                "search_volume": "1K+\n\n1,000%",
                "started": "21 hours ago\n\nLasted 5 hr",
                "related_topics": ""
            },
            {
                "title": "helen mcentee leaving cert",
                "search_volume": "500+\n\n1,000%",
                "started": "3 hours ago\n\nLasted 1 hr",
                "related_topics": ""
            },
            {
                "title": "wordle hint",
                "search_volume": "200+\n\n100%",
                "started": "4 hours ago\n\nLasted 1 hr",
                "related_topics": ""
            },
            {
                "title": "derry city fc vs sligo rovers",
                "search_volume": "500+\n\n1,000%",
                "started": "17 hours ago\n\nLasted 3 hr",
                "related_topics": ""
            }
        ],
        "GB": [
            {
                "title": "st. george's day",
                "search_volume": "200K+\n\n1,000%",
                "started": "12 hours ago\ntrending_up\nActive",
                "related_topics": ""
            },
            {
                "title": "man city vs aston villa",
                "search_volume": "200K+\n\n1,000%",
                "started": "20 hours ago\ntrending_up\nActive",
                "related_topics": ""
            },
            {
                "title": "pahalgam",
                "search_volume": "50K+\n\n1,000%",
                "started": "22 hours ago\ntrending_up\nActive",
                "related_topics": ""
            },
            {
                "title": "istanbul earthquake",
                "search_volume": "20K+\n\n1,000%",
                "started": "1 hour ago\ntrending_up\nActive",
                "related_topics": ""
            },
            {
                "title": "barcelona vs mallorca",
                "search_volume": "20K+\n\n1,000%",
                "started": "17 hours ago\ntrending_up\nActive",
                "related_topics": ""
            },
            {
                "title": "nantes vs psg",
                "search_volume": "20K+\n\n1,000%",
                "started": "17 hours ago\ntrending_up\nActive",
                "related_topics": ""
            },
            {
                "title": "oblivion remaster ps5",
                "search_volume": "50K+\n\n1,000%",
                "started": "20 hours ago\ntrending_up\nActive",
                "related_topics": ""
            },
            {
                "title": "angellica bell martin lewis",
                "search_volume": "50K+\n\n1,000%",
                "started": "15 hours ago\ntrending_up\nActive",
                "related_topics": ""
            },
            {
                "title": "hobbycraft stores closing",
                "search_volume": "20K+\n\n1,000%",
                "started": "16 hours ago\ntrending_up\nActive",
                "related_topics": ""
            },
            {
                "title": "istanbul deprem",
                "search_volume": "5K+\n\n1,000%",
                "started": "1 hour ago\ntrending_up\nActive",
                "related_topics": ""
            },
            {
                "title": "sophie nyweide",
                "search_volume": "10K+\n\n700%",
                "started": "19 hours ago\ntrending_up\nActive",
                "related_topics": ""
            },
            {
                "title": "thunderbolts",
                "search_volume": "10K+\n\n300%",
                "started": "14 hours ago\ntrending_up\nActive",
                "related_topics": ""
            },
            {
                "title": "earthquake",
                "search_volume": "2K+\n\n1,000%",
                "started": "1 hour ago\ntrending_up\nActive",
                "related_topics": ""
            },
            {
                "title": "marks and spencer uk",
                "search_volume": "20K+\n\n400%",
                "started": "20 hours ago\ntrending_up\nActive",
                "related_topics": ""
            },
            {
                "title": "i know what you did last summer",
                "search_volume": "10K+\n\n500%",
                "started": "22 hours ago\ntrending_up\nActive",
                "related_topics": ""
            },
            {
                "title": "clair obscur expedition 33",
                "search_volume": "2K+\n\n400%",
                "started": "2 hours ago\ntrending_up\nActive",
                "related_topics": ""
            },
            {
                "title": "prince louis",
                "search_volume": "2K+\n\n500%",
                "started": "6 hours ago\ntrending_up\nActive",
                "related_topics": ""
            },
            {
                "title": "tesla",
                "search_volume": "20K+\n\n200%",
                "started": "15 hours ago\ntrending_up\nActive",
                "related_topics": ""
            },
            {
                "title": "police vetting",
                "search_volume": "2K+\n\n700%",
                "started": "1 hour ago\ntrending_up\nActive",
                "related_topics": ""
            },
            {
                "title": "nerys lloyd",
                "search_volume": "2K+\n\n500%",
                "started": "1 hour ago\ntrending_up\nActive",
                "related_topics": ""
            },
            {
                "title": "carli norris",
                "search_volume": "2K+\n\n800%",
                "started": "9 hours ago\ntrending_up\nActive",
                "related_topics": ""
            },
            {
                "title": "peter andre",
                "search_volume": "5K+\n\n300%",
                "started": "23 hours ago\ntrending_up\nActive",
                "related_topics": ""
            },
            {
                "title": "maggie chapman",
                "search_volume": "2K+\n\n100%",
                "started": "23 hours ago\ntrending_up\nActive",
                "related_topics": ""
            },
            {
                "title": "louise thompson",
                "search_volume": "2K+\n\n1,000%",
                "started": "2 hours ago\ntrending_up\nActive",
                "related_topics": ""
            },
            {
                "title": "sharon osbourne",
                "search_volume": "5K+\n\n200%",
                "started": "14 hours ago\ntrending_up\nActive",
                "related_topics": ""
            }
        ],
        "US": [
            {
                "title": "sophie nyweide",
                "search_volume": "100K+\n\n1,000%",
                "started": "19 hours ago\ntrending_up\nActive",
                "related_topics": ""
            },
            {
                "title": "pahalgam",
                "search_volume": "200K+\n\n600%",
                "started": "22 hours ago\ntrending_up\nActive",
                "related_topics": ""
            },
            {
                "title": "barcelona - r.c.d. mallorca",
                "search_volume": "200K+\n\n1,000%",
                "started": "17 hours ago\ntrending_up\nActive",
                "related_topics": ""
            },
            {
                "title": "nj wildfire",
                "search_volume": "100K+\n\n500%",
                "started": "13 hours ago\ntrending_up\nActive",
                "related_topics": ""
            },
            {
                "title": "autism registry",
                "search_volume": "50K+\n\n1,000%",
                "started": "17 hours ago\ntrending_up\nActive",
                "related_topics": ""
            },
            {
                "title": "oblivion remaster ps5",
                "search_volume": "200K+\n\n1,000%",
                "started": "20 hours ago\ntrending_up\nActive",
                "related_topics": ""
            },
            {
                "title": "mike patrick",
                "search_volume": "50K+\n\n1,000%",
                "started": "14 hours ago\ntrending_up\nActive",
                "related_topics": ""
            },
            {
                "title": "lakers",
                "search_volume": "500K+\n\n500%",
                "started": "9 hours ago\ntrending_up\nActive",
                "related_topics": ""
            },
            {
                "title": "tesla stock",
                "search_volume": "500K+\n\n200%",
                "started": "15 hours ago\ntrending_up\nActive",
                "related_topics": ""
            },
            {
                "title": "dodgers vs cubs",
                "search_volume": "100K+\n\n1,000%",
                "started": "12 hours ago\ntrending_up\nActive",
                "related_topics": ""
            },
            {
                "title": "man city vs aston villa",
                "search_volume": "100K+\n\n1,000%",
                "started": "17 hours ago\ntrending_up\nActive",
                "related_topics": ""
            },
            {
                "title": "food dye ban",
                "search_volume": "50K+\n\n300%",
                "started": "16 hours ago\ntrending_up\nActive",
                "related_topics": ""
            },
            {
                "title": "gabbi zuniga",
                "search_volume": "20K+\n\n700%",
                "started": "13 hours ago\ntrending_up\nActive",
                "related_topics": ""
            },
            {
                "title": "mn wild",
                "search_volume": "50K+\n\n600%",
                "started": "8 hours ago\ntrending_up\nActive",
                "related_topics": ""
            },
            {
                "title": "sarah palin",
                "search_volume": "20K+\n\n500%",
                "started": "15 hours ago\ntrending_up\nActive",
                "related_topics": ""
            },
            {
                "title": "ron desantis",
                "search_volume": "20K+\n\n500%",
                "started": "16 hours ago\ntrending_up\nActive",
                "related_topics": ""
            },
            {
                "title": "mariners vs red sox",
                "search_volume": "20K+\n\n900%",
                "started": "13 hours ago\ntrending_up\nActive",
                "related_topics": ""
            },
            {
                "title": "thunderbolts",
                "search_volume": "20K+\n\n100%",
                "started": "13 hours ago\ntrending_up\nActive",
                "related_topics": ""
            },
            {
                "title": "lori vallow",
                "search_volume": "50K+\n\n400%",
                "started": "15 hours ago\ntrending_up\nActive",
                "related_topics": ""
            },
            {
                "title": "lightning game",
                "search_volume": "20K+\n\n300%",
                "started": "13 hours ago\ntrending_up\nActive",
                "related_topics": ""
            },
            {
                "title": "intel layoffs",
                "search_volume": "10K+\n\n600%",
                "started": "9 hours ago\ntrending_up\nActive",
                "related_topics": ""
            },
            {
                "title": "mel owens",
                "search_volume": "10K+\n\n500%",
                "started": "11 hours ago\ntrending_up\nActive",
                "related_topics": ""
            },
            {
                "title": "panthers vs lightning",
                "search_volume": "20K+\n\n800%",
                "started": "11 hours ago\ntrending_up\nActive",
                "related_topics": ""
            },
            {
                "title": "lil uzi vert",
                "search_volume": "20K+\n\n300%",
                "started": "18 hours ago\ntrending_up\nActive",
                "related_topics": ""
            },
            {
                "title": "rangers vs athletics",
                "search_volume": "10K+\n\n900%",
                "started": "10 hours ago\ntrending_up\nActive",
                "related_topics": ""
            }
        ]
    }
}