{
    "timestamp": "2025-06-28 19:00:27",
    "trends": {
        "IE": [
            {
                "title": "dublin v tyrone",
                "search_volume": "20K+\n\n1,000%",
                "started": "9 hours ago\ntrending_up\nActive",
                "related_topics": ""
            },
            {
                "title": "donegal v monaghan",
                "search_volume": "20K+\n\n1,000%",
                "started": "9 hours ago\ntrending_up\nActive",
                "related_topics": ""
            },
            {
                "title": "kneecap glastonbury",
                "search_volume": "10K+\n\n1,000%",
                "started": "23 hours ago\ntrending_up\nActive",
                "related_topics": ""
            },
            {
                "title": "barbarians vs south africa",
                "search_volume": "5K+\n\n800%",
                "started": "8 hours ago\ntrending_up\nActive",
                "related_topics": ""
            },
            {
                "title": "beabadoobee",
                "search_volume": "500+\n\n1,000%",
                "started": "40 minutes ago\ntrending_up\nActive",
                "related_topics": ""
            },
            {
                "title": "john fogerty",
                "search_volume": "1K+\n\n1,000%",
                "started": "1 hour ago\ntrending_up\nActive",
                "related_topics": ""
            },
            {
                "title": "waterford minor hurling",
                "search_volume": "1K+\n\n1,000%",
                "started": "1 hour ago\ntrending_up\nActive",
                "related_topics": ""
            },
            {
                "title": "palmeiras vs botafogo",
                "search_volume": "1K+\n\n1,000%",
                "started": "2 hours ago\ntrending_up\nActive",
                "related_topics": ""
            },
            {
                "title": "shefali jariwala",
                "search_volume": "2K+\n\n1,000%",
                "started": "22 hours ago\ntrending_up\nActive",
                "related_topics": ""
            },
            {
                "title": "emergency alerts",
                "search_volume": "500+\n\n1,000%",
                "started": "6 hours ago\ntrending_up\nActive",
                "related_topics": ""
            },
            {
                "title": "f1 qualifying",
                "search_volume": "1K+\n\n1,000%",
                "started": "6 hours ago\ntrending_up\nActive",
                "related_topics": ""
            },
            {
                "title": "stephen cluxton",
                "search_volume": "200+\n\n1,000%",
                "started": "30 minutes ago\ntrending_up\nActive",
                "related_topics": ""
            },
            {
                "title": "glastonbury 2025 lineup",
                "search_volume": "2K+\n\n300%",
                "started": "23 hours ago\ntrending_up\nActive",
                "related_topics": ""
            },
            {
                "title": "justin timberlake",
                "search_volume": "1K+\n\n200%",
                "started": "22 hours ago\ntrending_up\nActive",
                "related_topics": ""
            },
            {
                "title": "dublin",
                "search_volume": "5K+\n\n200%",
                "started": "40 minutes ago\ntrending_up\nActive",
                "related_topics": ""
            },
            {
                "title": "gaa fixtures today",
                "search_volume": "2K+\n\n100%",
                "started": "5 hours ago\n\nLasted 5 hr",
                "related_topics": ""
            },
            {
                "title": "lions",
                "search_volume": "10K+\n\n1,000%",
                "started": "8 hours ago\n\nLasted 3 hr",
                "related_topics": ""
            },
            {
                "title": "con o callaghan",
                "search_volume": "100+\n\n900%",
                "started": "40 minutes ago\ntrending_up\nActive",
                "related_topics": ""
            },
            {
                "title": "tyrone gaa",
                "search_volume": "100+\n\n800%",
                "started": "30 minutes ago\ntrending_up\nActive",
                "related_topics": ""
            },
            {
                "title": "clare gaa twitter",
                "search_volume": "100+\n\n800%",
                "started": "50 minutes ago\ntrending_up\nActive",
                "related_topics": ""
            },
            {
                "title": "the 1975",
                "search_volume": "10K+\n\n1,000%",
                "started": "22 hours ago\n\nLasted 21 hr",
                "related_topics": ""
            },
            {
                "title": "brandi carlile",
                "search_volume": "500+\n\n1,000%",
                "started": "1 hour ago\n\nLasted 1 hr",
                "related_topics": ""
            },
            {
                "title": "ufc 317",
                "search_volume": "500+\n\n100%",
                "started": "20 hours ago\ntrending_up\nActive",
                "related_topics": ""
            },
            {
                "title": "gaa live scores",
                "search_volume": "500+\n\n100%",
                "started": "2 hours ago\n\nLasted 1 hr",
                "related_topics": ""
            },
            {
                "title": "jake paul vs chavez jr",
                "search_volume": "100+\n\n200%",
                "started": "10 minutes ago\ntrending_up\nActive",
                "related_topics": ""
            }
        ],
        "GB": [
            {
                "title": "john fogerty",
                "search_volume": "20K+\n\n1,000%",
                "started": "23 hours ago\ntrending_up\nActive",
                "related_topics": ""
            },
            {
                "title": "pulp",
                "search_volume": "20K+\n\n1,000%",
                "started": "2 hours ago\ntrending_up\nActive",
                "related_topics": ""
            },
            {
                "title": "bob vylan",
                "search_volume": "20K+\n\n1,000%",
                "started": "4 hours ago\ntrending_up\nActive",
                "related_topics": ""
            },
            {
                "title": "shefali jariwala",
                "search_volume": "50K+\n\n1,000%",
                "started": "22 hours ago\ntrending_up\nActive",
                "related_topics": ""
            },
            {
                "title": "beabadoobee",
                "search_volume": "10K+\n\n1,000%",
                "started": "5 hours ago\ntrending_up\nActive",
                "related_topics": ""
            },
            {
                "title": "glastonbury festival pyramid stage",
                "search_volume": "20K+\n\n1,000%",
                "started": "11 hours ago\ntrending_up\nActive",
                "related_topics": ""
            },
            {
                "title": "brandi carlile",
                "search_volume": "20K+\n\n1,000%",
                "started": "5 hours ago\ntrending_up\nActive",
                "related_topics": ""
            },
            {
                "title": "gary numan",
                "search_volume": "10K+\n\n1,000%",
                "started": "5 hours ago\ntrending_up\nActive",
                "related_topics": ""
            },
            {
                "title": "the script",
                "search_volume": "20K+\n\n1,000%",
                "started": "4 hours ago\ntrending_up\nActive",
                "related_topics": ""
            },
            {
                "title": "denise welch",
                "search_volume": "20K+\n\n1,000%",
                "started": "22 hours ago\ntrending_up\nActive",
                "related_topics": ""
            },
            {
                "title": "1975 glastonbury",
                "search_volume": "50K+\n\n800%",
                "started": "23 hours ago\ntrending_up\nActive",
                "related_topics": ""
            },
            {
                "title": "palmeiras vs botafogo",
                "search_volume": "10K+\n\n1,000%",
                "started": "3 hours ago\ntrending_up\nActive",
                "related_topics": ""
            },
            {
                "title": "force vs british & irish lions",
                "search_volume": "100K+\n\n1,000%",
                "started": "8 hours ago\ntrending_up\nActive",
                "related_topics": ""
            },
            {
                "title": "skepta",
                "search_volume": "10K+\n\n900%",
                "started": "2 hours ago\ntrending_up\nActive",
                "related_topics": ""
            },
            {
                "title": "barbarians rugby",
                "search_volume": "10K+\n\n600%",
                "started": "7 hours ago\ntrending_up\nActive",
                "related_topics": ""
            },
            {
                "title": "f1 qualifying",
                "search_volume": "20K+\n\n1,000%",
                "started": "5 hours ago\ntrending_up\nActive",
                "related_topics": ""
            },
            {
                "title": "halifax bank",
                "search_volume": "5K+\n\n1,000%",
                "started": "18 hours ago\ntrending_up\nActive",
                "related_topics": ""
            },
            {
                "title": "rod stewart glastonbury",
                "search_volume": "10K+\n\n300%",
                "started": "24 hours ago\ntrending_up\nActive",
                "related_topics": ""
            },
            {
                "title": "jake paul vs chavez",
                "search_volume": "5K+\n\n200%",
                "started": "20 hours ago\ntrending_up\nActive",
                "related_topics": ""
            },
            {
                "title": "deontay wilder",
                "search_volume": "10K+\n\n600%",
                "started": "22 hours ago\ntrending_up\nActive",
                "related_topics": ""
            },
            {
                "title": "neil young glastonbury",
                "search_volume": "10K+\n\n200%",
                "started": "23 hours ago\ntrending_up\nActive",
                "related_topics": ""
            },
            {
                "title": "iron maiden",
                "search_volume": "5K+\n\n300%",
                "started": "7 hours ago\ntrending_up\nActive",
                "related_topics": ""
            },
            {
                "title": "jade",
                "search_volume": "5K+\n\n1,000%",
                "started": "3 hours ago\ntrending_up\nActive",
                "related_topics": ""
            },
            {
                "title": "india women vs england women",
                "search_volume": "5K+\n\n1,000%",
                "started": "4 hours ago\ntrending_up\nActive",
                "related_topics": ""
            },
            {
                "title": "south africa vs zimbabwe",
                "search_volume": "10K+\n\n1,000%",
                "started": "10 hours ago\ntrending_up\nActive",
                "related_topics": ""
            }
        ],
        "US": [
            {
                "title": "lonzo ball",
                "search_volume": "100K+\n\n1,000%",
                "started": "3 hours ago\ntrending_up\nActive",
                "related_topics": ""
            },
            {
                "title": "shefali jariwala",
                "search_volume": "100K+\n\n1,000%",
                "started": "22 hours ago\ntrending_up\nActive",
                "related_topics": ""
            },
            {
                "title": "athletics vs yankees",
                "search_volume": "50K+\n\n1,000%",
                "started": "19 hours ago\ntrending_up\nActive",
                "related_topics": ""
            },
            {
                "title": "fever vs wings",
                "search_volume": "100K+\n\n1,000%",
                "started": "20 hours ago\ntrending_up\nActive",
                "related_topics": ""
            },
            {
                "title": "twins vs tigers",
                "search_volume": "20K+\n\n900%",
                "started": "19 hours ago\ntrending_up\nActive",
                "related_topics": ""
            },
            {
                "title": "palmeiras vs botafogo",
                "search_volume": "50K+\n\n1,000%",
                "started": "11 hours ago\ntrending_up\nActive",
                "related_topics": ""
            },
            {
                "title": "palmeiras - botafogo",
                "search_volume": "20K+\n\n1,000%",
                "started": "2 hours ago\ntrending_up\nActive",
                "related_topics": ""
            },
            {
                "title": "antoine massey",
                "search_volume": "50K+\n\n1,000%",
                "started": "20 hours ago\ntrending_up\nActive",
                "related_topics": ""
            },
            {
                "title": "lauren sanchez wedding dress",
                "search_volume": "50K+\n\n600%",
                "started": "23 hours ago\ntrending_up\nActive",
                "related_topics": ""
            },
            {
                "title": "phillies vs braves",
                "search_volume": "50K+\n\n1,000%",
                "started": "19 hours ago\ntrending_up\nActive",
                "related_topics": ""
            },
            {
                "title": "sydney sweeney",
                "search_volume": "50K+\n\n300%",
                "started": "10 hours ago\ntrending_up\nActive",
                "related_topics": ""
            },
            {
                "title": "matthew schaefer",
                "search_volume": "20K+\n\n800%",
                "started": "20 hours ago\ntrending_up\nActive",
                "related_topics": ""
            },
            {
                "title": "mega millions",
                "search_volume": "50K+\n\n50%",
                "started": "12 hours ago\ntrending_up\nActive",
                "related_topics": ""
            },
            {
                "title": "dodgers vs royals",
                "search_volume": "20K+\n\n1,000%",
                "started": "18 hours ago\ntrending_up\nActive",
                "related_topics": ""
            },
            {
                "title": "john gibson",
                "search_volume": "10K+\n\n1,000%",
                "started": "1 hour ago\ntrending_up\nActive",
                "related_topics": ""
            },
            {
                "title": "jayne mansfield",
                "search_volume": "100K+\n\n300%",
                "started": "17 hours ago\ntrending_up\nActive",
                "related_topics": ""
            },
            {
                "title": "rays vs orioles",
                "search_volume": "50K+\n\n800%",
                "started": "19 hours ago\ntrending_up\nActive",
                "related_topics": ""
            },
            {
                "title": "wwe night of champions 2025 start time",
                "search_volume": "20K+\n\n300%",
                "started": "11 hours ago\ntrending_up\nActive",
                "related_topics": ""
            },
            {
                "title": "detachable parts of a dress form",
                "search_volume": "20K+\n\n500%",
                "started": "15 hours ago\ntrending_up\nActive",
                "related_topics": ""
            },
            {
                "title": "james hagens",
                "search_volume": "20K+\n\n600%",
                "started": "23 hours ago\ntrending_up\nActive",
                "related_topics": ""
            },
            {
                "title": "savannah bananas",
                "search_volume": "10K+\n\n700%",
                "started": "50 minutes ago\ntrending_up\nActive",
                "related_topics": ""
            },
            {
                "title": "kilmar \u00e1brego garc\u00eda",
                "search_volume": "5K+\n\n500%",
                "started": "6 hours ago\ntrending_up\nActive",
                "related_topics": ""
            },
            {
                "title": "ashanti alert",
                "search_volume": "20K+\n\n1,000%",
                "started": "6 hours ago\ntrending_up\nActive",
                "related_topics": ""
            },
            {
                "title": "russia ukraine",
                "search_volume": "10K+\n\n1,000%",
                "started": "4 hours ago\ntrending_up\nActive",
                "related_topics": ""
            },
            {
                "title": "naz reid",
                "search_volume": "20K+\n\n400%",
                "started": "22 hours ago\ntrending_up\nActive",
                "related_topics": ""
            }
        ]
    }
}